{
  "travelDetails": [
    {
      "date": "2017-10-14",
      "userId": 123,
      "schedule": [
        {
          "type": "transport",
          "status": "Confirmed",
          "from": "Moscow Airport",
          "to": "Hotel",
          "pickUpTime": "12:20",
          "dropOffTime": "12:20",
          "serviceType": "pool"
        }
      ]
    },
    {
      "date": "2017-09-20",
      "userId": 123,
      "schedule": [
        {
          "type": "transport",
          "status": "Confirmed",
          "from": "Moscow Airport",
          "to": "Hotel",
          "pickUpTime": "12:20",
          "dropOffTime": "12:20",
          "serviceType": "pool"
        }
      ]
    },
    {
      "date": "2017-09-15",
      "userId": 123,
      "schedule": [
        {
          "type": "flight",
          "status": "Confirmed",
          "from": "Zurich (ZRH)",
          "to": "Moscow (DME)",
          "departure": "12:20",
          "arrival": "12:20",
          "flightNumber": "LX 1345"
        },
        {
          "type": "transport",
          "status": "Confirmed",
          "from": "Moscow Airport",
          "to": "Hotel",
          "pickUpTime": "12:20",
          "dropOffTime": "12:20",
          "serviceType": "pool"
        },
        {
          "type": "event",
          "eventName": "Russia - New Zealand",
          "site": "Moscow arena",
          "city": "Moscow",
          "hour": "18:00",
          "tickets": 1
        },
        {
          "type": "accomodation",
          "status": "",
          "name": "Hotel Name Goes Here",
          "checkInTime": "12/07/2017 12:00",
          "checkOutTime": "14/07/2017 12:00"
        }
      ]
    },
    {
      "date": "2017-09-17",
      "userId": 123,
      "schedule": [
        {
          "type": "transport",
          "status": "Confirmed",
          "from": "Moscow Airport",
          "to": "Hotel",
          "pickUpTime": "12:20",
          "dropOffTime": "12:20",
          "serviceType": "pool"
        },
        {
          "type": "transport",
          "status": "Confirmed",
          "from": "Moscow Airport",
          "to": "Hotel",
          "pickUpTime": "12:20",
          "dropOffTime": "12:20",
          "serviceType": "pool"
        },
        {
          "type": "accomodation",
          "status": "",
          "name": "Hotel Name Goes Here",
          "checkInTime": "12/07/2017 12:00",
          "checkOutTime": "14/07/2017 12:00"
        }
      ]
    }
  ],
  "events": [
    {
      "name": "FIFA Beach Soccer World Cup Bahamas 2017",
      "timeRange": "27 April - 7 May",
      "userId": 123,
      "dates": ["2017-09-20", "2017-09-15",  "2017-10-14", "2017-09-17"]
    }
  ]
}

